staticfunc/__init__.py
staticfunc/_staticfunc.py
staticfunc/_test.py
staticfunc-0.0.1.dist-info/METADATA
staticfunc-0.0.1.dist-info/WHEEL
staticfunc-0.0.1.dist-info/licenses/LICENSE
staticfunc-0.0.1.dist-info/RECORD
